chibi_atlas/__init__.py
chibi_atlas/chibi_atlas.py
chibi_atlas/multi.py
chibi_atlas/tree.py
chibi_atlas-1.1.0.dist-info/AUTHORS.rst
chibi_atlas-1.1.0.dist-info/LICENSE
chibi_atlas-1.1.0.dist-info/METADATA
chibi_atlas-1.1.0.dist-info/WHEEL
chibi_atlas-1.1.0.dist-info/top_level.txt
chibi_atlas-1.1.0.dist-info/RECORD
