Metadata-Version: 2.1
Name: chibi_atlas
Version: 1.1.0
Summary: small lib to proccess the keys of the dict like attributes
Home-page: https://github.com/dem4ply/chibi_atlas
Author: dem4ply
Author-email: dem4ply@gmail.com
License: WTFPL
Keywords: chibi_atlas
Classifier: Development Status :: 5 - Production/Stable
Classifier: Intended Audience :: Developers
Classifier: License :: Public Domain
Classifier: Natural Language :: English
Classifier: Natural Language :: Spanish
Classifier: Programming Language :: Python :: 3.7
Classifier: Programming Language :: Python :: 3.8
Classifier: Programming Language :: Python :: 3.9
Classifier: Programming Language :: Python :: 3.10
Classifier: Programming Language :: Python :: 3.11
Classifier: Programming Language :: Python :: 3.12
Classifier: Programming Language :: Python :: 3.13
Classifier: Programming Language :: Python :: 3.14
Classifier: Topic :: Utilities
License-File: LICENSE
License-File: AUTHORS.rst
Requires-Dist: pyyaml >=5.1.2
